helper_functions/__init__.py
helper_functions/main.py
jl_helper_functions-0.2.4.dist-info/licenses/LICENSE.txt
jl_helper_functions-0.2.4.dist-info/METADATA
jl_helper_functions-0.2.4.dist-info/WHEEL
jl_helper_functions-0.2.4.dist-info/top_level.txt
jl_helper_functions-0.2.4.dist-info/RECORD
