Metadata-Version: 2.4
Name: JL_helper_functions
Version: 0.2.4
Summary: A collection of utility functions for various tasks, especially in scRNAseq analysis
License: 
Classifier: License :: OSI Approved :: MIT License
Classifier: Programming Language :: Python :: 3
Classifier: Programming Language :: Python :: 3.12
Requires-Python: >=3.12
License-File: LICENSE.txt
Requires-Dist: numpy
Requires-Dist: pandas
Requires-Dist: scipy
Requires-Dist: scanpy
Dynamic: license-file
